<aidashipmap>
    <ship id="BE" ShipName="AIDAbella" ShipLink="/aidabella">
        <route/>
        <nextport/>
        <data latitude="55.558617" longitude="9.756783" windSpeed="15.9" windAngle="W" windRelative="0" waterTemperature="15.8" airTemperature="0" timeOffsetUtc="+1.50" timestamp="2026-05-25T11:25:00+02:00" speed="0.1" localTime="11:24" heading="300.6" course="220"/>
        <cams>
            <cam name="Backbord" thumb="https://media.aida.de/webcam/aidabella_left_76px.jpg" link="https://media.aida.de/webcam/aidabella_left_625px.jpg" img="https://media.aida.de/webcam/aidabella_left_625px.jpg" captured="20260525111405"/>
            <cam name="Voraus" thumb="https://media.aida.de/webcam/aidabella_ahead_76px.jpg" link="https://media.aida.de/webcam/aidabella_ahead_625px.jpg" img="https://media.aida.de/webcam/aidabella_ahead_625px.jpg" captured="20260525111405"/>
            <cam name="Steuerbord" thumb="https://media.aida.de/webcam/aidabella_right_76px.jpg" link="https://media.aida.de/webcam/aidabella_right_625px.jpg" img="https://media.aida.de/webcam/aidabella_right_625px.jpg" captured="20260525111405"/>
        </cams>
    </ship>
    <ship id="BL" ShipName="AIDAblu" ShipLink="/aidablu">
        <route/>
        <nextport/>
        <data latitude="35.73425" longitude="23.41295" windSpeed="25.1" windAngle="NO" windRelative="0" waterTemperature="20.8" airTemperature="20" timeOffsetUtc="+2.50" timestamp="2026-05-25T11:25:00+02:00" speed="8.7" localTime="12:24" heading="68.3" course="74.7"/>
        <cams>
            <cam name="Backbord" thumb="https://media.aida.de/webcam/aidablu_left_76px.jpg" link="https://media.aida.de/webcam/aidablu_left_625px.jpg" img="https://media.aida.de/webcam/aidablu_left_625px.jpg" captured="20260525111407"/>
            <cam name="Voraus" thumb="https://media.aida.de/webcam/aidablu_ahead_76px.jpg" link="https://media.aida.de/webcam/aidablu_ahead_625px.jpg" img="https://media.aida.de/webcam/aidablu_ahead_625px.jpg" captured="20260525111407"/>
            <cam name="Steuerbord" thumb="https://media.aida.de/webcam/aidablu_right_76px.jpg" link="https://media.aida.de/webcam/aidablu_right_625px.jpg" img="https://media.aida.de/webcam/aidablu_right_625px.jpg" captured="20260525111407"/>
        </cams>
    </ship>
    <ship id="DI" ShipName="AIDAdiva" ShipLink="/aidadiva">
        <route/>
        <nextport/>
        <data latitude="58.13855" longitude="7.992533" windSpeed="15.6" windAngle="SW" windRelative="0" waterTemperature="8.2" airTemperature="15.6" timeOffsetUtc="+1.50" timestamp="2026-05-25T11:25:00+02:00" speed="0.3" localTime="11:24" heading="114" course="164.5"/>
        <cams>
            <cam name="Backbord" thumb="https://media.aida.de/webcam/aidadiva_left_76px.jpg" link="https://media.aida.de/webcam/aidadiva_left_625px.jpg" img="https://media.aida.de/webcam/aidadiva_left_625px.jpg" captured="20260523214414"/>
            <cam name="Voraus" thumb="https://media.aida.de/webcam/aidadiva_ahead_76px.jpg" link="https://media.aida.de/webcam/aidadiva_ahead_625px.jpg" img="https://media.aida.de/webcam/aidadiva_ahead_625px.jpg" captured="20260523214414"/>
            <cam name="Steuerbord" thumb="https://media.aida.de/webcam/aidadiva_right_76px.jpg" link="https://media.aida.de/webcam/aidadiva_right_625px.jpg" img="https://media.aida.de/webcam/aidadiva_right_625px.jpg" captured="20260523214414"/>
        </cams>
    </ship>
    <ship id="LU" ShipName="AIDAluna" ShipLink="/aidaluna">
        <route/>
        <nextport/>
        <data latitude="53.4072" longitude="-3.000483" windSpeed="10.5" windAngle="S" windRelative="0" waterTemperature="13.6" airTemperature="21.8" timeOffsetUtc="+0.50" timestamp="2026-05-25T11:25:00+02:00" speed="0.2" localTime="10:24" heading="157.8" course="67.8"/>
        <cams>
            <cam name="Backbord" thumb="https://media.aida.de/webcam/aidaluna_left_76px.jpg" link="https://media.aida.de/webcam/aidaluna_left_625px.jpg" img="https://media.aida.de/webcam/aidaluna_left_625px.jpg" captured="20260525111407"/>
            <cam name="Voraus" thumb="https://media.aida.de/webcam/aidaluna_ahead_76px.jpg" link="https://media.aida.de/webcam/aidaluna_ahead_625px.jpg" img="https://media.aida.de/webcam/aidaluna_ahead_625px.jpg" captured="20260525111407"/>
            <cam name="Steuerbord" thumb="https://media.aida.de/webcam/aidaluna_right_76px.jpg" link="https://media.aida.de/webcam/aidaluna_right_625px.jpg" img="https://media.aida.de/webcam/aidaluna_right_625px.jpg" captured="20260525111407"/>
        </cams>
    </ship>
    <ship id="MA" ShipName="AIDAmar" ShipLink="/aidamar">
        <route/>
        <nextport/>
        <data latitude="54.533833" longitude="18.55225" windSpeed="18.5" windAngle="W" windRelative="0" waterTemperature="14" airTemperature="20.3" timeOffsetUtc="+1.50" timestamp="2026-05-25T11:25:00+02:00" speed="0.2" localTime="11:24" heading="84.5" course="16.4"/>
        <cams>
            <cam name="Backbord" thumb="https://media.aida.de/webcam/aidamar_left_76px.jpg" link="https://media.aida.de/webcam/aidamar_left_625px.jpg" img="https://media.aida.de/webcam/aidamar_left_625px.jpg" captured="20260525111406"/>
            <cam name="Voraus" thumb="https://media.aida.de/webcam/aidamar_ahead_76px.jpg" link="https://media.aida.de/webcam/aidamar_ahead_625px.jpg" img="https://media.aida.de/webcam/aidamar_ahead_625px.jpg" captured="20260525111406"/>
            <cam name="Steuerbord" thumb="https://media.aida.de/webcam/aidamar_right_76px.jpg" link="https://media.aida.de/webcam/aidamar_right_625px.jpg" img="https://media.aida.de/webcam/aidamar_right_625px.jpg" captured="20260525111406"/>
        </cams>
    </ship>
    <ship id="ST" ShipName="AIDAstella" ShipLink="/aidastella">
        <route/>
        <nextport/>
        <data latitude="39.8837" longitude="4.293967" windSpeed="10.4" windAngle="O" windRelative="0" waterTemperature="21.9" airTemperature="21.5" timeOffsetUtc="+1.50" timestamp="2026-05-25T11:25:00+02:00" speed="7.4" localTime="11:24" heading="330.4" course="328.8"/>
        <cams>
            <cam name="Backbord" thumb="https://media.aida.de/webcam/aidastella_left_76px.jpg" link="https://media.aida.de/webcam/aidastella_left_625px.jpg" img="https://media.aida.de/webcam/aidastella_left_625px.jpg" captured="20260525111905"/>
            <cam name="Voraus" thumb="https://media.aida.de/webcam/aidastella_ahead_76px.jpg" link="https://media.aida.de/webcam/aidastella_ahead_625px.jpg" img="https://media.aida.de/webcam/aidastella_ahead_625px.jpg" captured="20260525111905"/>
            <cam name="Steuerbord" thumb="https://media.aida.de/webcam/aidastella_right_76px.jpg" link="https://media.aida.de/webcam/aidastella_right_625px.jpg" img="https://media.aida.de/webcam/aidastella_right_625px.jpg" captured="20260525111905"/>
        </cams>
    </ship>
    <ship id="SO" ShipName="AIDAsol" ShipLink="/aidasol">
        <route/>
        <nextport/>
        <data latitude="54.21525" longitude="4.351367" windSpeed="21" windAngle="SW" windRelative="0" waterTemperature="13.3" airTemperature="16" timeOffsetUtc="+0.50" timestamp="2026-05-25T11:25:00+02:00" speed="9.4" localTime="10:24" heading="284.1" course="286.8"/>
        <cams>
            <cam name="Backbord" thumb="https://media.aida.de/webcam/aidasol_left_76px.jpg" link="https://media.aida.de/webcam/aidasol_left_625px.jpg" img="https://media.aida.de/webcam/aidasol_left_625px.jpg" captured="20260525111406"/>
            <cam name="Voraus" thumb="https://media.aida.de/webcam/aidasol_ahead_76px.jpg" link="https://media.aida.de/webcam/aidasol_ahead_625px.jpg" img="https://media.aida.de/webcam/aidasol_ahead_625px.jpg" captured="20260525111406"/>
            <cam name="Steuerbord" thumb="https://media.aida.de/webcam/aidasol_right_76px.jpg" link="https://media.aida.de/webcam/aidasol_right_625px.jpg" img="https://media.aida.de/webcam/aidasol_right_625px.jpg" captured="20260525111406"/>
        </cams>
    </ship>
    <ship id="PR" ShipName="AIDAprima" ShipLink="/aidaprima">
        <route/>
        <nextport/>
        <data latitude="62.468917" longitude="6.156683" windSpeed="11.3" windAngle="SO" windRelative="0" waterTemperature="11.2" airTemperature="8.1" timeOffsetUtc="+1.50" timestamp="2026-05-25T11:25:00+02:00" speed="0" localTime="11:24" heading="92.9" course="92.9"/>
        <cams>
            <cam name="Backbord" thumb="https://media.aida.de/webcam/aidaprima_left_76px.jpg" link="https://media.aida.de/webcam/aidaprima_left_625px.jpg" img="https://media.aida.de/webcam/aidaprima_left_625px.jpg" captured="20260525111405"/>
            <cam name="Voraus" thumb="https://media.aida.de/webcam/aidaprima_ahead_76px.jpg" link="https://media.aida.de/webcam/aidaprima_ahead_625px.jpg" img="https://media.aida.de/webcam/aidaprima_ahead_625px.jpg" captured="20260525111405"/>
            <cam name="Steuerbord" thumb="https://media.aida.de/webcam/aidaprima_right_76px.jpg" link="https://media.aida.de/webcam/aidaprima_right_625px.jpg" img="https://media.aida.de/webcam/aidaprima_right_625px.jpg" captured="20260525111405"/>
        </cams>
    </ship>
    <ship id="PE" ShipName="AIDAperla" ShipLink="/aidaperla">
        <route/>
        <nextport/>
        <data latitude="59.4115" longitude="5.255183" windSpeed="6" windAngle="S" windRelative="0" waterTemperature="13.2" airTemperature="13.5" timeOffsetUtc="+1.50" timestamp="2026-05-25T11:25:00+02:00" speed="0.3" localTime="11:24" heading="306.6" course="278.3"/>
        <cams>
            <cam name="Backbord" thumb="https://media.aida.de/webcam/aidaperla_left_76px.jpg" link="https://media.aida.de/webcam/aidaperla_left_625px.jpg" img="https://media.aida.de/webcam/aidaperla_left_625px.jpg" captured="20260525111906"/>
            <cam name="Voraus" thumb="https://media.aida.de/webcam/aidaperla_ahead_76px.jpg" link="https://media.aida.de/webcam/aidaperla_ahead_625px.jpg" img="https://media.aida.de/webcam/aidaperla_ahead_625px.jpg" captured="20260525111906"/>
            <cam name="Steuerbord" thumb="https://media.aida.de/webcam/aidaperla_right_76px.jpg" link="https://media.aida.de/webcam/aidaperla_right_625px.jpg" img="https://media.aida.de/webcam/aidaperla_right_625px.jpg" captured="20260525111906"/>
        </cams>
    </ship>
    <ship id="NO" ShipName="AIDAnova" ShipLink="/aidanova">
        <route/>
        <nextport/>
        <data latitude="57.712967" longitude="10.585583" windSpeed="22.7" windAngle="W" windRelative="0" waterTemperature="8.9" airTemperature="15.4" timeOffsetUtc="+1.50" timestamp="2026-05-25T11:25:01+02:00" speed="0.4" localTime="11:24" heading="251.4" course="251.4"/>
        <cams>
            <cam name="Backbord" thumb="https://media.aida.de/webcam/aidanova_left_76px.jpg" link="https://media.aida.de/webcam/aidanova_left_625px.jpg" img="https://media.aida.de/webcam/aidanova_left_625px.jpg" captured="20260525111906"/>
            <cam name="Voraus" thumb="https://media.aida.de/webcam/aidanova_ahead_76px.jpg" link="https://media.aida.de/webcam/aidanova_ahead_625px.jpg" img="https://media.aida.de/webcam/aidanova_ahead_625px.jpg" captured="20260525111906"/>
            <cam name="Steuerbord" thumb="https://media.aida.de/webcam/aidanova_right_76px.jpg" link="https://media.aida.de/webcam/aidanova_right_625px.jpg" img="https://media.aida.de/webcam/aidanova_right_625px.jpg" captured="20260525111906"/>
        </cams>
    </ship>
    <ship id="CO" ShipName="AIDAcosma" ShipLink="/aidacosma">
        <route/>
        <nextport/>
        <data latitude="39.208383" longitude="9.106567" windSpeed="4.7" windAngle="S" windRelative="0" waterTemperature="19.4" airTemperature="23.5" timeOffsetUtc="+1.50" timestamp="2026-05-25T11:25:01+02:00" speed="0.2" localTime="11:24" heading="149.2" course="149.2"/>
        <cams>
            <cam name="Backbord" thumb="https://media.aida.de/webcam/aidacosma_left_76px.jpg" link="https://media.aida.de/webcam/aidacosma_left_625px.jpg" img="https://media.aida.de/webcam/aidacosma_left_625px.jpg" captured="20260525111906"/>
            <cam name="Voraus" thumb="https://media.aida.de/webcam/aidacosma_ahead_76px.jpg" link="https://media.aida.de/webcam/aidacosma_ahead_625px.jpg" img="https://media.aida.de/webcam/aidacosma_ahead_625px.jpg" captured="20260525111906"/>
            <cam name="Steuerbord" thumb="https://media.aida.de/webcam/aidacosma_right_76px.jpg" link="https://media.aida.de/webcam/aidacosma_right_625px.jpg" img="https://media.aida.de/webcam/aidacosma_right_625px.jpg" captured="20260525111906"/>
        </cams>
    </ship>
</aidashipmap>