<aidashipmap>
    <ship id="BE" ShipName="AIDAbella" ShipLink="/aidabella">
        <route/>
        <nextport/>
        <data latitude="56.079567" longitude="11.13325" windSpeed="33.3" windAngle="NW" windRelative="0" waterTemperature="18.1" airTemperature="12.5" timeOffsetUtc="+2.00" timestamp="2026-07-06T01:05:00+02:00" speed="19.1" localTime="01:04" heading="20.4" course="21.9"/>
        <cams>
            <cam name="Backbord" thumb="https://media.aida.de/webcam/aidabella_left_76px.jpg" link="https://media.aida.de/webcam/aidabella_left_625px.jpg" img="https://media.aida.de/webcam/aidabella_left_625px.jpg" captured="20260706005414"/>
            <cam name="Voraus" thumb="https://media.aida.de/webcam/aidabella_ahead_76px.jpg" link="https://media.aida.de/webcam/aidabella_ahead_625px.jpg" img="https://media.aida.de/webcam/aidabella_ahead_625px.jpg" captured="20260706005414"/>
            <cam name="Steuerbord" thumb="https://media.aida.de/webcam/aidabella_right_76px.jpg" link="https://media.aida.de/webcam/aidabella_right_625px.jpg" img="https://media.aida.de/webcam/aidabella_right_625px.jpg" captured="20260706005414"/>
        </cams>
    </ship>
    <ship id="BL" ShipName="AIDAblu" ShipLink="/aidablu">
        <route/>
        <nextport/>
        <data latitude="36.5143" longitude="15.511717" windSpeed="2.2" windAngle="O" windRelative="0" waterTemperature="16.6" airTemperature="26.3" timeOffsetUtc="+2.00" timestamp="2026-07-06T01:05:00+02:00" speed="8.5" localTime="01:04" heading="237.6" course="236.9"/>
        <cams>
            <cam name="Backbord" thumb="https://media.aida.de/webcam/aidablu_left_76px.jpg" link="https://media.aida.de/webcam/aidablu_left_625px.jpg" img="https://media.aida.de/webcam/aidablu_left_625px.jpg" captured="20260706005415"/>
            <cam name="Voraus" thumb="https://media.aida.de/webcam/aidablu_ahead_76px.jpg" link="https://media.aida.de/webcam/aidablu_ahead_625px.jpg" img="https://media.aida.de/webcam/aidablu_ahead_625px.jpg" captured="20260706005415"/>
            <cam name="Steuerbord" thumb="https://media.aida.de/webcam/aidablu_right_76px.jpg" link="https://media.aida.de/webcam/aidablu_right_625px.jpg" img="https://media.aida.de/webcam/aidablu_right_625px.jpg" captured="20260706005415"/>
        </cams>
    </ship>
    <ship id="DI" ShipName="AIDAdiva" ShipLink="/aidadiva">
        <route/>
        <nextport/>
        <data latitude="57.874933" longitude="9.55425" windSpeed="29.3" windAngle="NW" windRelative="0" waterTemperature="14.6" airTemperature="14.7" timeOffsetUtc="+2.00" timestamp="2026-07-06T01:05:00+02:00" speed="13.4" localTime="01:04" heading="274.5" course="273.3"/>
        <cams>
            <cam name="Backbord" thumb="https://media.aida.de/webcam/aidadiva_left_76px.jpg" link="https://media.aida.de/webcam/aidadiva_left_625px.jpg" img="https://media.aida.de/webcam/aidadiva_left_625px.jpg" captured="20260706005415"/>
            <cam name="Voraus" thumb="https://media.aida.de/webcam/aidadiva_ahead_76px.jpg" link="https://media.aida.de/webcam/aidadiva_ahead_625px.jpg" img="https://media.aida.de/webcam/aidadiva_ahead_625px.jpg" captured="20260706005415"/>
            <cam name="Steuerbord" thumb="https://media.aida.de/webcam/aidadiva_right_76px.jpg" link="https://media.aida.de/webcam/aidadiva_right_625px.jpg" img="https://media.aida.de/webcam/aidadiva_right_625px.jpg" captured="20260706005415"/>
        </cams>
    </ship>
    <ship id="LU" ShipName="AIDAluna" ShipLink="/aidaluna">
        <route/>
        <nextport/>
        <data latitude="59.192933" longitude="5.114083" windSpeed="9.6" windAngle="W" windRelative="0" waterTemperature="15.4" airTemperature="11.9" timeOffsetUtc="+2.00" timestamp="2026-07-06T01:05:00+02:00" speed="18.3" localTime="01:04" heading="178.1" course="177.3"/>
        <cams>
            <cam name="Backbord" thumb="https://media.aida.de/webcam/aidaluna_left_76px.jpg" link="https://media.aida.de/webcam/aidaluna_left_625px.jpg" img="https://media.aida.de/webcam/aidaluna_left_625px.jpg" captured="20260706005414"/>
            <cam name="Voraus" thumb="https://media.aida.de/webcam/aidaluna_ahead_76px.jpg" link="https://media.aida.de/webcam/aidaluna_ahead_625px.jpg" img="https://media.aida.de/webcam/aidaluna_ahead_625px.jpg" captured="20260706005414"/>
            <cam name="Steuerbord" thumb="https://media.aida.de/webcam/aidaluna_right_76px.jpg" link="https://media.aida.de/webcam/aidaluna_right_625px.jpg" img="https://media.aida.de/webcam/aidaluna_right_625px.jpg" captured="20260706005414"/>
        </cams>
    </ship>
    <ship id="MA" ShipName="AIDAmar" ShipLink="/aidamar">
        <route/>
        <nextport/>
        <data latitude="51.888967" longitude="4.296567" windSpeed="9.3" windAngle="S" windRelative="0" waterTemperature="24.6" airTemperature="19.1" timeOffsetUtc="+2.00" timestamp="2026-07-06T01:05:00+02:00" speed="-0.8" localTime="01:04" heading="252.1" course="252.1"/>
        <cams>
            <cam name="Backbord" thumb="https://media.aida.de/webcam/aidamar_left_76px.jpg" link="https://media.aida.de/webcam/aidamar_left_625px.jpg" img="https://media.aida.de/webcam/aidamar_left_625px.jpg" captured="20260706005414"/>
            <cam name="Voraus" thumb="https://media.aida.de/webcam/aidamar_ahead_76px.jpg" link="https://media.aida.de/webcam/aidamar_ahead_625px.jpg" img="https://media.aida.de/webcam/aidamar_ahead_625px.jpg" captured="20260706005414"/>
            <cam name="Steuerbord" thumb="https://media.aida.de/webcam/aidamar_right_76px.jpg" link="https://media.aida.de/webcam/aidamar_right_625px.jpg" img="https://media.aida.de/webcam/aidamar_right_625px.jpg" captured="20260706005414"/>
        </cams>
    </ship>
    <ship id="ST" ShipName="AIDAstella" ShipLink="/aidastella">
        <route/>
        <nextport/>
        <data latitude="38.246267" longitude="12.5662" windSpeed="7" windAngle="NO" windRelative="0" waterTemperature="26.7" airTemperature="27" timeOffsetUtc="+2.00" timestamp="2026-07-06T01:05:00+02:00" speed="7.3" localTime="01:04" heading="76.3" course="76.5"/>
        <cams>
            <cam name="Backbord" thumb="https://media.aida.de/webcam/aidastella_left_76px.jpg" link="https://media.aida.de/webcam/aidastella_left_625px.jpg" img="https://media.aida.de/webcam/aidastella_left_625px.jpg" captured="20260706005415"/>
            <cam name="Voraus" thumb="https://media.aida.de/webcam/aidastella_ahead_76px.jpg" link="https://media.aida.de/webcam/aidastella_ahead_625px.jpg" img="https://media.aida.de/webcam/aidastella_ahead_625px.jpg" captured="20260706005415"/>
            <cam name="Steuerbord" thumb="https://media.aida.de/webcam/aidastella_right_76px.jpg" link="https://media.aida.de/webcam/aidastella_right_625px.jpg" img="https://media.aida.de/webcam/aidastella_right_625px.jpg" captured="20260706005415"/>
        </cams>
    </ship>
    <ship id="SO" ShipName="AIDAsol" ShipLink="/aidasol">
        <route/>
        <nextport/>
        <data latitude="54.199983" longitude="7.5781" windSpeed="19.9" windAngle="W" windRelative="0" waterTemperature="17.6" airTemperature="15.6" timeOffsetUtc="+2.00" timestamp="2026-07-06T01:05:00+02:00" speed="15.5" localTime="01:04" heading="299.8" course="300.6"/>
        <cams>
            <cam name="Backbord" thumb="https://media.aida.de/webcam/aidasol_left_76px.jpg" link="https://media.aida.de/webcam/aidasol_left_625px.jpg" img="https://media.aida.de/webcam/aidasol_left_625px.jpg" captured="20260706005414"/>
            <cam name="Voraus" thumb="https://media.aida.de/webcam/aidasol_ahead_76px.jpg" link="https://media.aida.de/webcam/aidasol_ahead_625px.jpg" img="https://media.aida.de/webcam/aidasol_ahead_625px.jpg" captured="20260706005414"/>
            <cam name="Steuerbord" thumb="https://media.aida.de/webcam/aidasol_right_76px.jpg" link="https://media.aida.de/webcam/aidasol_right_625px.jpg" img="https://media.aida.de/webcam/aidasol_right_625px.jpg" captured="20260706005414"/>
        </cams>
    </ship>
    <ship id="PR" ShipName="AIDAprima" ShipLink="/aidaprima">
        <route/>
        <nextport/>
        <data latitude="62.295767" longitude="7.005967" windSpeed="7.4" windAngle="O" windRelative="0" waterTemperature="14.7" airTemperature="8.9" timeOffsetUtc="+2.00" timestamp="2026-07-06T01:05:00+02:00" speed="7.2" localTime="01:03" heading="309.2" course="309.9"/>
        <cams>
            <cam name="Backbord" thumb="https://media.aida.de/webcam/aidaprima_left_76px.jpg" link="https://media.aida.de/webcam/aidaprima_left_625px.jpg" img="https://media.aida.de/webcam/aidaprima_left_625px.jpg" captured="20260706005414"/>
            <cam name="Voraus" thumb="https://media.aida.de/webcam/aidaprima_ahead_76px.jpg" link="https://media.aida.de/webcam/aidaprima_ahead_625px.jpg" img="https://media.aida.de/webcam/aidaprima_ahead_625px.jpg" captured="20260706005414"/>
            <cam name="Steuerbord" thumb="https://media.aida.de/webcam/aidaprima_right_76px.jpg" link="https://media.aida.de/webcam/aidaprima_right_625px.jpg" img="https://media.aida.de/webcam/aidaprima_right_625px.jpg" captured="20260706005414"/>
        </cams>
    </ship>
    <ship id="PE" ShipName="AIDAperla" ShipLink="/aidaperla">
        <route/>
        <nextport/>
        <data latitude="59.62015" longitude="4.135767" windSpeed="5.5" windAngle="NW" windRelative="0" waterTemperature="17" airTemperature="11.8" timeOffsetUtc="+2.00" timestamp="2026-07-06T01:05:00+02:00" speed="14.5" localTime="01:04" heading="3.9" course="5.2"/>
        <cams>
            <cam name="Backbord" thumb="https://media.aida.de/webcam/aidaperla_left_76px.jpg" link="https://media.aida.de/webcam/aidaperla_left_625px.jpg" img="https://media.aida.de/webcam/aidaperla_left_625px.jpg" captured="20260706005916"/>
            <cam name="Voraus" thumb="https://media.aida.de/webcam/aidaperla_ahead_76px.jpg" link="https://media.aida.de/webcam/aidaperla_ahead_625px.jpg" img="https://media.aida.de/webcam/aidaperla_ahead_625px.jpg" captured="20260706005916"/>
            <cam name="Steuerbord" thumb="https://media.aida.de/webcam/aidaperla_right_76px.jpg" link="https://media.aida.de/webcam/aidaperla_right_625px.jpg" img="https://media.aida.de/webcam/aidaperla_right_625px.jpg" captured="20260706005916"/>
        </cams>
    </ship>
    <ship id="NO" ShipName="AIDAnova" ShipLink="/aidanova">
        <route/>
        <nextport/>
        <data latitude="58.6726" longitude="10.753767" windSpeed="26.1" windAngle="NW" windRelative="0" waterTemperature="18.1" airTemperature="17" timeOffsetUtc="+2.00" timestamp="2026-07-06T01:05:01+02:00" speed="11.7" localTime="01:04" heading="344.7" course="346.1"/>
        <cams>
            <cam name="Backbord" thumb="https://media.aida.de/webcam/aidanova_left_76px.jpg" link="https://media.aida.de/webcam/aidanova_left_625px.jpg" img="https://media.aida.de/webcam/aidanova_left_625px.jpg" captured="20260706005944"/>
            <cam name="Voraus" thumb="https://media.aida.de/webcam/aidanova_ahead_76px.jpg" link="https://media.aida.de/webcam/aidanova_ahead_625px.jpg" img="https://media.aida.de/webcam/aidanova_ahead_625px.jpg" captured="20260706005944"/>
            <cam name="Steuerbord" thumb="https://media.aida.de/webcam/aidanova_right_76px.jpg" link="https://media.aida.de/webcam/aidanova_right_625px.jpg" img="https://media.aida.de/webcam/aidanova_right_625px.jpg" captured="20260706005944"/>
        </cams>
    </ship>
    <ship id="CO" ShipName="AIDAcosma" ShipLink="/aidacosma">
        <route/>
        <nextport/>
        <data latitude="38.768883" longitude="8.3643" windSpeed="10" windAngle="NW" windRelative="0" waterTemperature="25.5" airTemperature="24.8" timeOffsetUtc="+2.00" timestamp="2026-07-06T01:05:01+02:00" speed="8.3" localTime="01:03" heading="96.3" course="97.5"/>
        <cams>
            <cam name="Backbord" thumb="https://media.aida.de/webcam/aidacosma_left_76px.jpg" link="https://media.aida.de/webcam/aidacosma_left_625px.jpg" img="https://media.aida.de/webcam/aidacosma_left_625px.jpg" captured="20260706005415"/>
            <cam name="Voraus" thumb="https://media.aida.de/webcam/aidacosma_ahead_76px.jpg" link="https://media.aida.de/webcam/aidacosma_ahead_625px.jpg" img="https://media.aida.de/webcam/aidacosma_ahead_625px.jpg" captured="20260706005415"/>
            <cam name="Steuerbord" thumb="https://media.aida.de/webcam/aidacosma_right_76px.jpg" link="https://media.aida.de/webcam/aidacosma_right_625px.jpg" img="https://media.aida.de/webcam/aidacosma_right_625px.jpg" captured="20260706005415"/>
        </cams>
    </ship>
</aidashipmap>