<aidashipmap>
    <ship id="BE" ShipName="AIDAbella" ShipLink="/aidabella">
        <route/>
        <nextport/>
        <data latitude="0" longitude="0" windSpeed="0" windAngle="N" windRelative="0" waterTemperature="0" airTemperature="0" timeOffsetUtc="+0" timestamp="2026-02-15T13:10:00+01:00" speed="0" localTime="" heading="0" course="0"/>
        <cams>
            <cam name="Backbord" thumb="https://media.aida.de/webcam/aidabella_left_76px.jpg" link="https://media.aida.de/webcam/aidabella_left_625px.jpg" img="https://media.aida.de/webcam/aidabella_left_625px.jpg" captured="20260215130413"/>
            <cam name="Voraus" thumb="https://media.aida.de/webcam/aidabella_ahead_76px.jpg" link="https://media.aida.de/webcam/aidabella_ahead_625px.jpg" img="https://media.aida.de/webcam/aidabella_ahead_625px.jpg" captured="20260215130413"/>
            <cam name="Steuerbord" thumb="https://media.aida.de/webcam/aidabella_right_76px.jpg" link="https://media.aida.de/webcam/aidabella_right_625px.jpg" img="https://media.aida.de/webcam/aidabella_right_625px.jpg" captured="20260215130413"/>
        </cams>
    </ship>
    <ship id="BL" ShipName="AIDAblu" ShipLink="/aidablu">
        <route/>
        <nextport/>
        <data latitude="14.599933" longitude="-61.061283" windSpeed="8.8" windAngle="O" windRelative="0" waterTemperature="27.3" airTemperature="25.6" timeOffsetUtc="-4.00" timestamp="2026-02-15T13:10:00+01:00" speed="-0.2" localTime="08:09" heading="222.4" course="40.1"/>
        <cams>
            <cam name="Backbord" thumb="https://media.aida.de/webcam/aidablu_left_76px.jpg" link="https://media.aida.de/webcam/aidablu_left_625px.jpg" img="https://media.aida.de/webcam/aidablu_left_625px.jpg" captured="20260215130426"/>
            <cam name="Voraus" thumb="https://media.aida.de/webcam/aidablu_ahead_76px.jpg" link="https://media.aida.de/webcam/aidablu_ahead_625px.jpg" img="https://media.aida.de/webcam/aidablu_ahead_625px.jpg" captured="20260215130426"/>
            <cam name="Steuerbord" thumb="https://media.aida.de/webcam/aidablu_right_76px.jpg" link="https://media.aida.de/webcam/aidablu_right_625px.jpg" img="https://media.aida.de/webcam/aidablu_right_625px.jpg" captured="20260215130426"/>
        </cams>
    </ship>
    <ship id="DI" ShipName="AIDAdiva" ShipLink="/aidadiva">
        <route/>
        <nextport/>
        <data latitude="4.18515" longitude="73.505283" windSpeed="18" windAngle="NO" windRelative="0" waterTemperature="28.7" airTemperature="27.9" timeOffsetUtc="+5.00" timestamp="2026-02-15T13:10:00+01:00" speed="0.8" localTime="17:09" heading="345.9" course="17.1"/>
        <cams>
            <cam name="Backbord" thumb="https://media.aida.de/webcam/aidadiva_left_76px.jpg" link="https://media.aida.de/webcam/aidadiva_left_625px.jpg" img="https://media.aida.de/webcam/aidadiva_left_625px.jpg" captured="20260215130413"/>
            <cam name="Voraus" thumb="https://media.aida.de/webcam/aidadiva_ahead_76px.jpg" link="https://media.aida.de/webcam/aidadiva_ahead_625px.jpg" img="https://media.aida.de/webcam/aidadiva_ahead_625px.jpg" captured="20260215130413"/>
            <cam name="Steuerbord" thumb="https://media.aida.de/webcam/aidadiva_right_76px.jpg" link="https://media.aida.de/webcam/aidadiva_right_625px.jpg" img="https://media.aida.de/webcam/aidadiva_right_625px.jpg" captured="20260215130413"/>
        </cams>
    </ship>
    <ship id="LU" ShipName="AIDAluna" ShipLink="/aidaluna">
        <route/>
        <nextport/>
        <data latitude="28.140783" longitude="-15.422883" windSpeed="10.5" windAngle="NO" windRelative="0" waterTemperature="18.5" airTemperature="18.2" timeOffsetUtc="+0.00" timestamp="2026-02-15T13:10:00+01:00" speed="0" localTime="12:09" heading="316.1" course="172.6"/>
        <cams>
            <cam name="Backbord" thumb="https://media.aida.de/webcam/aidaluna_left_76px.jpg" link="https://media.aida.de/webcam/aidaluna_left_625px.jpg" img="https://media.aida.de/webcam/aidaluna_left_625px.jpg" captured="20260215130413"/>
            <cam name="Voraus" thumb="https://media.aida.de/webcam/aidaluna_ahead_76px.jpg" link="https://media.aida.de/webcam/aidaluna_ahead_625px.jpg" img="https://media.aida.de/webcam/aidaluna_ahead_625px.jpg" captured="20260215130413"/>
            <cam name="Steuerbord" thumb="https://media.aida.de/webcam/aidaluna_right_76px.jpg" link="https://media.aida.de/webcam/aidaluna_right_625px.jpg" img="https://media.aida.de/webcam/aidaluna_right_625px.jpg" captured="20260215130413"/>
        </cams>
    </ship>
    <ship id="MA" ShipName="AIDAmar" ShipLink="/aidamar">
        <route/>
        <nextport/>
        <data latitude="-23.9527" longitude="-46.309617" windSpeed="0" windAngle="SW" windRelative="0" waterTemperature="28" airTemperature="29.8" timeOffsetUtc="-3.00" timestamp="2026-02-15T13:10:00+01:00" speed="0" localTime="09:09" heading="145.8" course="145.8"/>
        <cams>
            <cam name="Backbord" thumb="https://media.aida.de/webcam/aidamar_left_76px.jpg" link="https://media.aida.de/webcam/aidamar_left_625px.jpg" img="https://media.aida.de/webcam/aidamar_left_625px.jpg" captured="20260215130416"/>
            <cam name="Voraus" thumb="https://media.aida.de/webcam/aidamar_ahead_76px.jpg" link="https://media.aida.de/webcam/aidamar_ahead_625px.jpg" img="https://media.aida.de/webcam/aidamar_ahead_625px.jpg" captured="20260215130416"/>
            <cam name="Steuerbord" thumb="https://media.aida.de/webcam/aidamar_right_76px.jpg" link="https://media.aida.de/webcam/aidamar_right_625px.jpg" img="https://media.aida.de/webcam/aidamar_right_625px.jpg" captured="20260215130416"/>
        </cams>
    </ship>
    <ship id="ST" ShipName="AIDAstella" ShipLink="/aidastella">
        <route/>
        <nextport/>
        <data latitude="-20.932633" longitude="55.318967" windSpeed="9.5" windAngle="W" windRelative="0" waterTemperature="29.1" airTemperature="30.5" timeOffsetUtc="+4.00" timestamp="2026-02-15T13:10:00+01:00" speed="0.2" localTime="16:09" heading="85.2" course="2.9"/>
        <cams>
            <cam name="Backbord" thumb="https://media.aida.de/webcam/aidastella_left_76px.jpg" link="https://media.aida.de/webcam/aidastella_left_625px.jpg" img="https://media.aida.de/webcam/aidastella_left_625px.jpg" captured="20260215130421"/>
            <cam name="Voraus" thumb="https://media.aida.de/webcam/aidastella_ahead_76px.jpg" link="https://media.aida.de/webcam/aidastella_ahead_625px.jpg" img="https://media.aida.de/webcam/aidastella_ahead_625px.jpg" captured="20260215130421"/>
            <cam name="Steuerbord" thumb="https://media.aida.de/webcam/aidastella_right_76px.jpg" link="https://media.aida.de/webcam/aidastella_right_625px.jpg" img="https://media.aida.de/webcam/aidastella_right_625px.jpg" captured="20260215130421"/>
        </cams>
    </ship>
    <ship id="SO" ShipName="AIDAsol" ShipLink="/aidasol">
        <route/>
        <nextport/>
        <data latitude="17.7523" longitude="-67.75105" windSpeed="32.5" windAngle="NO" windRelative="0" waterTemperature="27.3" airTemperature="25" timeOffsetUtc="-4.00" timestamp="2026-02-15T13:10:00+01:00" speed="13.5" localTime="08:09" heading="96.8" course="102.6"/>
        <cams>
            <cam name="Backbord" thumb="https://media.aida.de/webcam/aidasol_left_76px.jpg" link="https://media.aida.de/webcam/aidasol_left_625px.jpg" img="https://media.aida.de/webcam/aidasol_left_625px.jpg" captured="20260215130417"/>
            <cam name="Voraus" thumb="https://media.aida.de/webcam/aidasol_ahead_76px.jpg" link="https://media.aida.de/webcam/aidasol_ahead_625px.jpg" img="https://media.aida.de/webcam/aidasol_ahead_625px.jpg" captured="20260215130417"/>
            <cam name="Steuerbord" thumb="https://media.aida.de/webcam/aidasol_right_76px.jpg" link="https://media.aida.de/webcam/aidasol_right_625px.jpg" img="https://media.aida.de/webcam/aidasol_right_625px.jpg" captured="20260215130417"/>
        </cams>
    </ship>
    <ship id="PR" ShipName="AIDAprima" ShipLink="/aidaprima">
        <route/>
        <nextport/>
        <data latitude="54.326" longitude="10.1479" windSpeed="1.2" windAngle="O" windRelative="0" waterTemperature="1.4" airTemperature="-2" timeOffsetUtc="+1.00" timestamp="2026-02-15T13:10:00+01:00" speed="0.2" localTime="13:09" heading="31" course="165.2"/>
        <cams>
            <cam name="Backbord" thumb="https://media.aida.de/webcam/aidaprima_left_76px.jpg" link="https://media.aida.de/webcam/aidaprima_left_625px.jpg" img="https://media.aida.de/webcam/aidaprima_left_625px.jpg" captured="20260215130413"/>
            <cam name="Voraus" thumb="https://media.aida.de/webcam/aidaprima_ahead_76px.jpg" link="https://media.aida.de/webcam/aidaprima_ahead_625px.jpg" img="https://media.aida.de/webcam/aidaprima_ahead_625px.jpg" captured="20260215130413"/>
            <cam name="Steuerbord" thumb="https://media.aida.de/webcam/aidaprima_right_76px.jpg" link="https://media.aida.de/webcam/aidaprima_right_625px.jpg" img="https://media.aida.de/webcam/aidaprima_right_625px.jpg" captured="20260215130413"/>
        </cams>
    </ship>
    <ship id="PE" ShipName="AIDAperla" ShipLink="/aidaperla">
        <route/>
        <nextport/>
        <data latitude="12.105033" longitude="-68.944333" windSpeed="16.3" windAngle="O" windRelative="0" waterTemperature="27.2" airTemperature="26.8" timeOffsetUtc="-4.00" timestamp="2026-02-15T13:10:01+01:00" speed="0" localTime="08:09" heading="108.6" course="344.6"/>
        <cams>
            <cam name="Backbord" thumb="https://media.aida.de/webcam/aidaperla_left_76px.jpg" link="https://media.aida.de/webcam/aidaperla_left_625px.jpg" img="https://media.aida.de/webcam/aidaperla_left_625px.jpg" captured="20260215130919"/>
            <cam name="Voraus" thumb="https://media.aida.de/webcam/aidaperla_ahead_76px.jpg" link="https://media.aida.de/webcam/aidaperla_ahead_625px.jpg" img="https://media.aida.de/webcam/aidaperla_ahead_625px.jpg" captured="20260215130919"/>
            <cam name="Steuerbord" thumb="https://media.aida.de/webcam/aidaperla_right_76px.jpg" link="https://media.aida.de/webcam/aidaperla_right_625px.jpg" img="https://media.aida.de/webcam/aidaperla_right_625px.jpg" captured="20260215130919"/>
        </cams>
    </ship>
    <ship id="NO" ShipName="AIDAnova" ShipLink="/aidanova">
        <route/>
        <nextport/>
        <data latitude="53.656317" longitude="5.524117" windSpeed="35" windAngle="SO" windRelative="0" waterTemperature="3.8" airTemperature="1.8" timeOffsetUtc="+1.00" timestamp="2026-02-15T13:10:01+01:00" speed="7.6" localTime="13:09" heading="231.6" course="251.5"/>
        <cams>
            <cam name="Backbord" thumb="https://media.aida.de/webcam/aidanova_left_76px.jpg" link="https://media.aida.de/webcam/aidanova_left_625px.jpg" img="https://media.aida.de/webcam/aidanova_left_625px.jpg" captured="20260215130915"/>
            <cam name="Voraus" thumb="https://media.aida.de/webcam/aidanova_ahead_76px.jpg" link="https://media.aida.de/webcam/aidanova_ahead_625px.jpg" img="https://media.aida.de/webcam/aidanova_ahead_625px.jpg" captured="20260215130915"/>
            <cam name="Steuerbord" thumb="https://media.aida.de/webcam/aidanova_right_76px.jpg" link="https://media.aida.de/webcam/aidanova_right_625px.jpg" img="https://media.aida.de/webcam/aidanova_right_625px.jpg" captured="20260215130915"/>
        </cams>
    </ship>
    <ship id="CO" ShipName="AIDAcosma" ShipLink="/aidacosma">
        <route/>
        <nextport/>
        <data latitude="30.133183" longitude="-15.96435" windSpeed="36.7" windAngle="NO" windRelative="0" waterTemperature="19.8" airTemperature="17" timeOffsetUtc="+0.00" timestamp="2026-02-15T13:10:01+01:00" speed="10.1" localTime="12:09" heading="353.4" course="342.9"/>
        <cams>
            <cam name="Backbord" thumb="https://media.aida.de/webcam/aidacosma_left_76px.jpg" link="https://media.aida.de/webcam/aidacosma_left_625px.jpg" img="https://media.aida.de/webcam/aidacosma_left_625px.jpg" captured="20260215130915"/>
            <cam name="Voraus" thumb="https://media.aida.de/webcam/aidacosma_ahead_76px.jpg" link="https://media.aida.de/webcam/aidacosma_ahead_625px.jpg" img="https://media.aida.de/webcam/aidacosma_ahead_625px.jpg" captured="20260215130915"/>
            <cam name="Steuerbord" thumb="https://media.aida.de/webcam/aidacosma_right_76px.jpg" link="https://media.aida.de/webcam/aidacosma_right_625px.jpg" img="https://media.aida.de/webcam/aidacosma_right_625px.jpg" captured="20260215130915"/>
        </cams>
    </ship>
</aidashipmap>