<aidashipmap>
    <ship id="BE" ShipName="AIDAbella" ShipLink="/aidabella">
        <route/>
        <nextport/>
        <data latitude="54.325533" longitude="10.14735" windSpeed="4.9" windAngle="SW" windRelative="0" waterTemperature="9.2" airTemperature="8.8" timeOffsetUtc="+1.50" timestamp="2026-04-22T08:45:00+02:00" speed="-0.1" localTime="08:44" heading="32" course="163.5"/>
        <cams>
            <cam name="Backbord" thumb="https://media.aida.de/webcam/aidabella_left_76px.jpg" link="https://media.aida.de/webcam/aidabella_left_625px.jpg" img="https://media.aida.de/webcam/aidabella_left_625px.jpg" captured="20260422083405"/>
            <cam name="Voraus" thumb="https://media.aida.de/webcam/aidabella_ahead_76px.jpg" link="https://media.aida.de/webcam/aidabella_ahead_625px.jpg" img="https://media.aida.de/webcam/aidabella_ahead_625px.jpg" captured="20260422083405"/>
            <cam name="Steuerbord" thumb="https://media.aida.de/webcam/aidabella_right_76px.jpg" link="https://media.aida.de/webcam/aidabella_right_625px.jpg" img="https://media.aida.de/webcam/aidabella_right_625px.jpg" captured="20260422083405"/>
        </cams>
    </ship>
    <ship id="BL" ShipName="AIDAblu" ShipLink="/aidablu">
        <route/>
        <nextport/>
        <data latitude="28.5242" longitude="-17.742567" windSpeed="8.8" windAngle="N" windRelative="0" waterTemperature="19.7" airTemperature="16.9" timeOffsetUtc="+0.50" timestamp="2026-04-22T08:45:01+02:00" speed="15.5" localTime="07:44" heading="21" course="21.9"/>
        <cams>
            <cam name="Backbord" thumb="https://media.aida.de/webcam/aidablu_left_76px.jpg" link="https://media.aida.de/webcam/aidablu_left_625px.jpg" img="https://media.aida.de/webcam/aidablu_left_625px.jpg" captured="20260422083405"/>
            <cam name="Voraus" thumb="https://media.aida.de/webcam/aidablu_ahead_76px.jpg" link="https://media.aida.de/webcam/aidablu_ahead_625px.jpg" img="https://media.aida.de/webcam/aidablu_ahead_625px.jpg" captured="20260422083405"/>
            <cam name="Steuerbord" thumb="https://media.aida.de/webcam/aidablu_right_76px.jpg" link="https://media.aida.de/webcam/aidablu_right_625px.jpg" img="https://media.aida.de/webcam/aidablu_right_625px.jpg" captured="20260422083405"/>
        </cams>
    </ship>
    <ship id="DI" ShipName="AIDAdiva" ShipLink="/aidadiva">
        <route/>
        <nextport/>
        <data latitude="57.6301" longitude="18.266517" windSpeed="10.5" windAngle="N" windRelative="0" waterTemperature="5.4" airTemperature="6" timeOffsetUtc="+1.50" timestamp="2026-04-22T08:45:00+02:00" speed="-0.1" localTime="08:44" heading="285.7" course="285.6"/>
        <cams>
            <cam name="Backbord" thumb="https://media.aida.de/webcam/aidadiva_left_76px.jpg" link="https://media.aida.de/webcam/aidadiva_left_625px.jpg" img="https://media.aida.de/webcam/aidadiva_left_625px.jpg" captured="20260422083405"/>
            <cam name="Voraus" thumb="https://media.aida.de/webcam/aidadiva_ahead_76px.jpg" link="https://media.aida.de/webcam/aidadiva_ahead_625px.jpg" img="https://media.aida.de/webcam/aidadiva_ahead_625px.jpg" captured="20260422083405"/>
            <cam name="Steuerbord" thumb="https://media.aida.de/webcam/aidadiva_right_76px.jpg" link="https://media.aida.de/webcam/aidadiva_right_625px.jpg" img="https://media.aida.de/webcam/aidadiva_right_625px.jpg" captured="20260422083405"/>
        </cams>
    </ship>
    <ship id="LU" ShipName="AIDAluna" ShipLink="/aidaluna">
        <route/>
        <nextport/>
        <data latitude="61.093217" longitude="6.582533" windSpeed="4.3" windAngle="S" windRelative="0" waterTemperature="2.6" airTemperature="5" timeOffsetUtc="+1.50" timestamp="2026-04-22T08:45:00+02:00" speed="0.4" localTime="08:44" heading="179.3" course="313.1"/>
        <cams>
            <cam name="Backbord" thumb="https://media.aida.de/webcam/aidaluna_left_76px.jpg" link="https://media.aida.de/webcam/aidaluna_left_625px.jpg" img="https://media.aida.de/webcam/aidaluna_left_625px.jpg" captured="20260422083404"/>
            <cam name="Voraus" thumb="https://media.aida.de/webcam/aidaluna_ahead_76px.jpg" link="https://media.aida.de/webcam/aidaluna_ahead_625px.jpg" img="https://media.aida.de/webcam/aidaluna_ahead_625px.jpg" captured="20260422083404"/>
            <cam name="Steuerbord" thumb="https://media.aida.de/webcam/aidaluna_right_76px.jpg" link="https://media.aida.de/webcam/aidaluna_right_625px.jpg" img="https://media.aida.de/webcam/aidaluna_right_625px.jpg" captured="20260422083404"/>
        </cams>
    </ship>
    <ship id="MA" ShipName="AIDAmar" ShipLink="/aidamar">
        <route/>
        <nextport/>
        <data latitude="59.905583" longitude="10.7468" windSpeed="2.3" windAngle="SW" windRelative="0" waterTemperature="9.2" airTemperature="9.5" timeOffsetUtc="+1.50" timestamp="2026-04-22T08:45:01+02:00" speed="-0.2" localTime="08:44" heading="19.2" course="19.2"/>
        <cams>
            <cam name="Backbord" thumb="https://media.aida.de/webcam/aidamar_left_76px.jpg" link="https://media.aida.de/webcam/aidamar_left_625px.jpg" img="https://media.aida.de/webcam/aidamar_left_625px.jpg" captured="20260422083404"/>
            <cam name="Voraus" thumb="https://media.aida.de/webcam/aidamar_ahead_76px.jpg" link="https://media.aida.de/webcam/aidamar_ahead_625px.jpg" img="https://media.aida.de/webcam/aidamar_ahead_625px.jpg" captured="20260422083404"/>
            <cam name="Steuerbord" thumb="https://media.aida.de/webcam/aidamar_right_76px.jpg" link="https://media.aida.de/webcam/aidamar_right_625px.jpg" img="https://media.aida.de/webcam/aidamar_right_625px.jpg" captured="20260422083404"/>
        </cams>
    </ship>
    <ship id="ST" ShipName="AIDAstella" ShipLink="/aidastella">
        <route/>
        <nextport/>
        <data latitude="36.8361" longitude="30.607683" windSpeed="3.1" windAngle="SO" windRelative="0" waterTemperature="18.9" airTemperature="17.5" timeOffsetUtc="+2.50" timestamp="2026-04-22T08:45:01+02:00" speed="-0.1" localTime="09:44" heading="332.2" course="332.2"/>
        <cams>
            <cam name="Backbord" thumb="https://media.aida.de/webcam/aidastella_left_76px.jpg" link="https://media.aida.de/webcam/aidastella_left_625px.jpg" img="https://media.aida.de/webcam/aidastella_left_625px.jpg" captured="20260422083404"/>
            <cam name="Voraus" thumb="https://media.aida.de/webcam/aidastella_ahead_76px.jpg" link="https://media.aida.de/webcam/aidastella_ahead_625px.jpg" img="https://media.aida.de/webcam/aidastella_ahead_625px.jpg" captured="20260422083404"/>
            <cam name="Steuerbord" thumb="https://media.aida.de/webcam/aidastella_right_76px.jpg" link="https://media.aida.de/webcam/aidastella_right_625px.jpg" img="https://media.aida.de/webcam/aidastella_right_625px.jpg" captured="20260422083404"/>
        </cams>
    </ship>
    <ship id="SO" ShipName="AIDAsol" ShipLink="/aidasol">
        <route/>
        <nextport/>
        <data latitude="59.000667" longitude="-2.975083" windSpeed="6" windAngle="O" windRelative="0" waterTemperature="8.7" airTemperature="7.1" timeOffsetUtc="+0.50" timestamp="2026-04-22T08:45:01+02:00" speed="0.4" localTime="07:44" heading="304.4" course="117.9"/>
        <cams>
            <cam name="Backbord" thumb="https://media.aida.de/webcam/aidasol_left_76px.jpg" link="https://media.aida.de/webcam/aidasol_left_625px.jpg" img="https://media.aida.de/webcam/aidasol_left_625px.jpg" captured="20260422083405"/>
            <cam name="Voraus" thumb="https://media.aida.de/webcam/aidasol_ahead_76px.jpg" link="https://media.aida.de/webcam/aidasol_ahead_625px.jpg" img="https://media.aida.de/webcam/aidasol_ahead_625px.jpg" captured="20260422083405"/>
            <cam name="Steuerbord" thumb="https://media.aida.de/webcam/aidasol_right_76px.jpg" link="https://media.aida.de/webcam/aidasol_right_625px.jpg" img="https://media.aida.de/webcam/aidasol_right_625px.jpg" captured="20260422083405"/>
        </cams>
    </ship>
    <ship id="PR" ShipName="AIDAprima" ShipLink="/aidaprima">
        <route/>
        <nextport/>
        <data latitude="55.425167" longitude="6.44075" windSpeed="18.5" windAngle="N" windRelative="0" waterTemperature="11.9" airTemperature="5.2" timeOffsetUtc="+1.50" timestamp="2026-04-22T08:45:01+02:00" speed="15.2" localTime="08:44" heading="333" course="332.1"/>
        <cams>
            <cam name="Backbord" thumb="https://media.aida.de/webcam/aidaprima_left_76px.jpg" link="https://media.aida.de/webcam/aidaprima_left_625px.jpg" img="https://media.aida.de/webcam/aidaprima_left_625px.jpg" captured="20260422083405"/>
            <cam name="Voraus" thumb="https://media.aida.de/webcam/aidaprima_ahead_76px.jpg" link="https://media.aida.de/webcam/aidaprima_ahead_625px.jpg" img="https://media.aida.de/webcam/aidaprima_ahead_625px.jpg" captured="20260422083405"/>
            <cam name="Steuerbord" thumb="https://media.aida.de/webcam/aidaprima_right_76px.jpg" link="https://media.aida.de/webcam/aidaprima_right_625px.jpg" img="https://media.aida.de/webcam/aidaprima_right_625px.jpg" captured="20260422083405"/>
        </cams>
    </ship>
    <ship id="PE" ShipName="AIDAperla" ShipLink="/aidaperla">
        <route/>
        <nextport/>
        <data latitude="51.376367" longitude="3.17295" windSpeed="29" windAngle="O" windRelative="0" waterTemperature="11.4" airTemperature="9.4" timeOffsetUtc="+1.50" timestamp="2026-04-22T08:45:01+02:00" speed="14.6" localTime="08:44" heading="134.1" course="136.6"/>
        <cams>
            <cam name="Backbord" thumb="https://media.aida.de/webcam/aidaperla_left_76px.jpg" link="https://media.aida.de/webcam/aidaperla_left_625px.jpg" img="https://media.aida.de/webcam/aidaperla_left_625px.jpg" captured="20260422083907"/>
            <cam name="Voraus" thumb="https://media.aida.de/webcam/aidaperla_ahead_76px.jpg" link="https://media.aida.de/webcam/aidaperla_ahead_625px.jpg" img="https://media.aida.de/webcam/aidaperla_ahead_625px.jpg" captured="20260422083907"/>
            <cam name="Steuerbord" thumb="https://media.aida.de/webcam/aidaperla_right_76px.jpg" link="https://media.aida.de/webcam/aidaperla_right_625px.jpg" img="https://media.aida.de/webcam/aidaperla_right_625px.jpg" captured="20260422083907"/>
        </cams>
    </ship>
    <ship id="NO" ShipName="AIDAnova" ShipLink="/aidanova">
        <route/>
        <nextport/>
        <data latitude="62.46885" longitude="6.158317" windSpeed="2.9" windAngle="NW" windRelative="0" waterTemperature="7.3" airTemperature="11.1" timeOffsetUtc="+1.50" timestamp="2026-04-22T08:45:01+02:00" speed="0" localTime="08:44" heading="93" course="3"/>
        <cams>
            <cam name="Backbord" thumb="https://media.aida.de/webcam/aidanova_left_76px.jpg" link="https://media.aida.de/webcam/aidanova_left_625px.jpg" img="https://media.aida.de/webcam/aidanova_left_625px.jpg" captured="20260422082906"/>
            <cam name="Voraus" thumb="https://media.aida.de/webcam/aidanova_ahead_76px.jpg" link="https://media.aida.de/webcam/aidanova_ahead_625px.jpg" img="https://media.aida.de/webcam/aidanova_ahead_625px.jpg" captured="20260422082906"/>
            <cam name="Steuerbord" thumb="https://media.aida.de/webcam/aidanova_right_76px.jpg" link="https://media.aida.de/webcam/aidanova_right_625px.jpg" img="https://media.aida.de/webcam/aidanova_right_625px.jpg" captured="20260422082906"/>
        </cams>
    </ship>
    <ship id="CO" ShipName="AIDAcosma" ShipLink="/aidacosma">
        <route/>
        <nextport/>
        <data latitude="41.921083" longitude="8.741433" windSpeed="3.3" windAngle="NO" windRelative="0" waterTemperature="17.8" airTemperature="19.1" timeOffsetUtc="+1.50" timestamp="2026-04-22T08:45:01+02:00" speed="0.4" localTime="08:44" heading="285.7" course="286.5"/>
        <cams>
            <cam name="Backbord" thumb="https://media.aida.de/webcam/aidacosma_left_76px.jpg" link="https://media.aida.de/webcam/aidacosma_left_625px.jpg" img="https://media.aida.de/webcam/aidacosma_left_625px.jpg" captured="20260422083406"/>
            <cam name="Voraus" thumb="https://media.aida.de/webcam/aidacosma_ahead_76px.jpg" link="https://media.aida.de/webcam/aidacosma_ahead_625px.jpg" img="https://media.aida.de/webcam/aidacosma_ahead_625px.jpg" captured="20260422083406"/>
            <cam name="Steuerbord" thumb="https://media.aida.de/webcam/aidacosma_right_76px.jpg" link="https://media.aida.de/webcam/aidacosma_right_625px.jpg" img="https://media.aida.de/webcam/aidacosma_right_625px.jpg" captured="20260422083406"/>
        </cams>
    </ship>
</aidashipmap>