<aidashipmap>
    <ship id="BE" ShipName="AIDAbella" ShipLink="/aidabella">
        <route/>
        <nextport/>
        <data latitude="28.905467" longitude="-13.534533" windSpeed="20.3" windAngle="NW" windRelative="0" waterTemperature="18.6" airTemperature="15.8" timeOffsetUtc="+0.00" timestamp="2026-04-10T06:55:00+02:00" speed="4.3" localTime="05:54" heading="356.5" course="4.9"/>
        <cams>
            <cam name="Backbord" thumb="https://media.aida.de/webcam/aidabella_left_76px.jpg" link="https://media.aida.de/webcam/aidabella_left_625px.jpg" img="https://media.aida.de/webcam/aidabella_left_625px.jpg" captured="20260410064415"/>
            <cam name="Voraus" thumb="https://media.aida.de/webcam/aidabella_ahead_76px.jpg" link="https://media.aida.de/webcam/aidabella_ahead_625px.jpg" img="https://media.aida.de/webcam/aidabella_ahead_625px.jpg" captured="20260410064415"/>
            <cam name="Steuerbord" thumb="https://media.aida.de/webcam/aidabella_right_76px.jpg" link="https://media.aida.de/webcam/aidabella_right_625px.jpg" img="https://media.aida.de/webcam/aidabella_right_625px.jpg" captured="20260410064415"/>
        </cams>
    </ship>
    <ship id="BL" ShipName="AIDAblu" ShipLink="/aidablu">
        <route/>
        <nextport/>
        <data latitude="18.905833" longitude="-66.8691" windSpeed="17.9" windAngle="SO" windRelative="0" waterTemperature="27" airTemperature="26.3" timeOffsetUtc="-5.00" timestamp="2026-04-10T06:55:00+02:00" speed="17.9" localTime="00:54" heading="275.5" course="277.3"/>
        <cams>
            <cam name="Backbord" thumb="https://media.aida.de/webcam/aidablu_left_76px.jpg" link="https://media.aida.de/webcam/aidablu_left_625px.jpg" img="https://media.aida.de/webcam/aidablu_left_625px.jpg" captured="20260410064415"/>
            <cam name="Voraus" thumb="https://media.aida.de/webcam/aidablu_ahead_76px.jpg" link="https://media.aida.de/webcam/aidablu_ahead_625px.jpg" img="https://media.aida.de/webcam/aidablu_ahead_625px.jpg" captured="20260410064415"/>
            <cam name="Steuerbord" thumb="https://media.aida.de/webcam/aidablu_right_76px.jpg" link="https://media.aida.de/webcam/aidablu_right_625px.jpg" img="https://media.aida.de/webcam/aidablu_right_625px.jpg" captured="20260410064415"/>
        </cams>
    </ship>
    <ship id="DI" ShipName="AIDAdiva" ShipLink="/aidadiva">
        <route/>
        <nextport/>
        <data latitude="55.101417" longitude="14.667633" windSpeed="31.5" windAngle="SO" windRelative="0" waterTemperature="4.4" airTemperature="2.7" timeOffsetUtc="+1.00" timestamp="2026-04-10T06:55:00+02:00" speed="6" localTime="06:54" heading="139.8" course="136.8"/>
        <cams>
            <cam name="Backbord" thumb="https://media.aida.de/webcam/aidadiva_left_76px.jpg" link="https://media.aida.de/webcam/aidadiva_left_625px.jpg" img="https://media.aida.de/webcam/aidadiva_left_625px.jpg" captured="20260326055415"/>
            <cam name="Voraus" thumb="https://media.aida.de/webcam/aidadiva_ahead_76px.jpg" link="https://media.aida.de/webcam/aidadiva_ahead_625px.jpg" img="https://media.aida.de/webcam/aidadiva_ahead_625px.jpg" captured="20260326055415"/>
            <cam name="Steuerbord" thumb="https://media.aida.de/webcam/aidadiva_right_76px.jpg" link="https://media.aida.de/webcam/aidadiva_right_625px.jpg" img="https://media.aida.de/webcam/aidadiva_right_625px.jpg" captured="20260326055415"/>
        </cams>
    </ship>
    <ship id="LU" ShipName="AIDAluna" ShipLink="/aidaluna">
        <route/>
        <nextport/>
        <data latitude="53.804567" longitude="6.22155" windSpeed="39.2" windAngle="W" windRelative="0" waterTemperature="4.4" airTemperature="7.7" timeOffsetUtc="+0.00" timestamp="2026-04-10T06:55:00+02:00" speed="13.8" localTime="05:54" heading="254.9" course="251.7"/>
        <cams>
            <cam name="Backbord" thumb="https://media.aida.de/webcam/aidaluna_left_76px.jpg" link="https://media.aida.de/webcam/aidaluna_left_625px.jpg" img="https://media.aida.de/webcam/aidaluna_left_625px.jpg" captured="20260410064420"/>
            <cam name="Voraus" thumb="https://media.aida.de/webcam/aidaluna_ahead_76px.jpg" link="https://media.aida.de/webcam/aidaluna_ahead_625px.jpg" img="https://media.aida.de/webcam/aidaluna_ahead_625px.jpg" captured="20260410064420"/>
            <cam name="Steuerbord" thumb="https://media.aida.de/webcam/aidaluna_right_76px.jpg" link="https://media.aida.de/webcam/aidaluna_right_625px.jpg" img="https://media.aida.de/webcam/aidaluna_right_625px.jpg" captured="20260410064420"/>
        </cams>
    </ship>
    <ship id="MA" ShipName="AIDAmar" ShipLink="/aidamar">
        <route/>
        <nextport/>
        <data latitude="53.542967" longitude="9.937783" windSpeed="9.3" windAngle="SO" windRelative="0" waterTemperature="10.6" airTemperature="5" timeOffsetUtc="+1.00" timestamp="2026-04-10T06:55:00+02:00" speed="-0.3" localTime="06:54" heading="268.9" course="282.6"/>
        <cams>
            <cam name="Backbord" thumb="https://media.aida.de/webcam/aidamar_left_76px.jpg" link="https://media.aida.de/webcam/aidamar_left_625px.jpg" img="https://media.aida.de/webcam/aidamar_left_625px.jpg" captured="20260410064415"/>
            <cam name="Voraus" thumb="https://media.aida.de/webcam/aidamar_ahead_76px.jpg" link="https://media.aida.de/webcam/aidamar_ahead_625px.jpg" img="https://media.aida.de/webcam/aidamar_ahead_625px.jpg" captured="20260410064415"/>
            <cam name="Steuerbord" thumb="https://media.aida.de/webcam/aidamar_right_76px.jpg" link="https://media.aida.de/webcam/aidamar_right_625px.jpg" img="https://media.aida.de/webcam/aidamar_right_625px.jpg" captured="20260410064415"/>
        </cams>
    </ship>
    <ship id="ST" ShipName="AIDAstella" ShipLink="/aidastella">
        <route/>
        <nextport/>
        <data latitude="37.9389" longitude="23.627267" windSpeed="2.9" windAngle="N" windRelative="0" waterTemperature="19" airTemperature="14.3" timeOffsetUtc="+2.00" timestamp="2026-04-10T06:55:00+02:00" speed="0.1" localTime="07:54" heading="248.3" course="248.3"/>
        <cams>
            <cam name="Backbord" thumb="https://media.aida.de/webcam/aidastella_left_76px.jpg" link="https://media.aida.de/webcam/aidastella_left_625px.jpg" img="https://media.aida.de/webcam/aidastella_left_625px.jpg" captured="20260410064915"/>
            <cam name="Voraus" thumb="https://media.aida.de/webcam/aidastella_ahead_76px.jpg" link="https://media.aida.de/webcam/aidastella_ahead_625px.jpg" img="https://media.aida.de/webcam/aidastella_ahead_625px.jpg" captured="20260410064915"/>
            <cam name="Steuerbord" thumb="https://media.aida.de/webcam/aidastella_right_76px.jpg" link="https://media.aida.de/webcam/aidastella_right_625px.jpg" img="https://media.aida.de/webcam/aidastella_right_625px.jpg" captured="20260410064915"/>
        </cams>
    </ship>
    <ship id="SO" ShipName="AIDAsol" ShipLink="/aidasol">
        <route/>
        <nextport/>
        <data latitude="49.497817" longitude="0.0278" windSpeed="10.6" windAngle="N" windRelative="0" waterTemperature="11.8" airTemperature="9.2" timeOffsetUtc="+1.00" timestamp="2026-04-10T06:55:00+02:00" speed="13.7" localTime="06:54" heading="104" course="106.9"/>
        <cams>
            <cam name="Backbord" thumb="https://media.aida.de/webcam/aidasol_left_76px.jpg" link="https://media.aida.de/webcam/aidasol_left_625px.jpg" img="https://media.aida.de/webcam/aidasol_left_625px.jpg" captured="20260410064415"/>
            <cam name="Voraus" thumb="https://media.aida.de/webcam/aidasol_ahead_76px.jpg" link="https://media.aida.de/webcam/aidasol_ahead_625px.jpg" img="https://media.aida.de/webcam/aidasol_ahead_625px.jpg" captured="20260410064415"/>
            <cam name="Steuerbord" thumb="https://media.aida.de/webcam/aidasol_right_76px.jpg" link="https://media.aida.de/webcam/aidasol_right_625px.jpg" img="https://media.aida.de/webcam/aidasol_right_625px.jpg" captured="20260410064415"/>
        </cams>
    </ship>
    <ship id="PR" ShipName="AIDAprima" ShipLink="/aidaprima">
        <route/>
        <nextport/>
        <data latitude="59.344017" longitude="18.127133" windSpeed="7" windAngle="SO" windRelative="0" waterTemperature="11" airTemperature="1.1" timeOffsetUtc="+1.00" timestamp="2026-04-10T06:55:00+02:00" speed="0" localTime="06:54" heading="242.1" course="242.2"/>
        <cams>
            <cam name="Backbord" thumb="https://media.aida.de/webcam/aidaprima_left_76px.jpg" link="https://media.aida.de/webcam/aidaprima_left_625px.jpg" img="https://media.aida.de/webcam/aidaprima_left_625px.jpg" captured="20260410064414"/>
            <cam name="Voraus" thumb="https://media.aida.de/webcam/aidaprima_ahead_76px.jpg" link="https://media.aida.de/webcam/aidaprima_ahead_625px.jpg" img="https://media.aida.de/webcam/aidaprima_ahead_625px.jpg" captured="20260410064414"/>
            <cam name="Steuerbord" thumb="https://media.aida.de/webcam/aidaprima_right_76px.jpg" link="https://media.aida.de/webcam/aidaprima_right_625px.jpg" img="https://media.aida.de/webcam/aidaprima_right_625px.jpg" captured="20260410064414"/>
        </cams>
    </ship>
    <ship id="PE" ShipName="AIDAperla" ShipLink="/aidaperla">
        <route/>
        <nextport/>
        <data latitude="53.530583" longitude="9.960517" windSpeed="5.1" windAngle="O" windRelative="0" waterTemperature="10.1" airTemperature="4.2" timeOffsetUtc="+1.00" timestamp="2026-04-10T06:55:01+02:00" speed="0.1" localTime="06:54" heading="306.5" course="161.7"/>
        <cams>
            <cam name="Backbord" thumb="https://media.aida.de/webcam/aidaperla_left_76px.jpg" link="https://media.aida.de/webcam/aidaperla_left_625px.jpg" img="https://media.aida.de/webcam/aidaperla_left_625px.jpg" captured="20260410064915"/>
            <cam name="Voraus" thumb="https://media.aida.de/webcam/aidaperla_ahead_76px.jpg" link="https://media.aida.de/webcam/aidaperla_ahead_625px.jpg" img="https://media.aida.de/webcam/aidaperla_ahead_625px.jpg" captured="20260410064915"/>
            <cam name="Steuerbord" thumb="https://media.aida.de/webcam/aidaperla_right_76px.jpg" link="https://media.aida.de/webcam/aidaperla_right_625px.jpg" img="https://media.aida.de/webcam/aidaperla_right_625px.jpg" captured="20260410064915"/>
        </cams>
    </ship>
    <ship id="NO" ShipName="AIDAnova" ShipLink="/aidanova">
        <route/>
        <nextport/>
        <data latitude="57.4277" longitude="7.9778" windSpeed="34.4" windAngle="SO" windRelative="0" waterTemperature="6.7" airTemperature="2.6" timeOffsetUtc="+1.00" timestamp="2026-04-10T06:55:01+02:00" speed="15.1" localTime="06:54" heading="205.2" course="211"/>
        <cams>
            <cam name="Backbord" thumb="https://media.aida.de/webcam/aidanova_left_76px.jpg" link="https://media.aida.de/webcam/aidanova_left_625px.jpg" img="https://media.aida.de/webcam/aidanova_left_625px.jpg" captured="20260410064915"/>
            <cam name="Voraus" thumb="https://media.aida.de/webcam/aidanova_ahead_76px.jpg" link="https://media.aida.de/webcam/aidanova_ahead_625px.jpg" img="https://media.aida.de/webcam/aidanova_ahead_625px.jpg" captured="20260410064915"/>
            <cam name="Steuerbord" thumb="https://media.aida.de/webcam/aidanova_right_76px.jpg" link="https://media.aida.de/webcam/aidanova_right_625px.jpg" img="https://media.aida.de/webcam/aidanova_right_625px.jpg" captured="20260410064915"/>
        </cams>
    </ship>
    <ship id="CO" ShipName="AIDAcosma" ShipLink="/aidacosma">
        <route/>
        <nextport/>
        <data latitude="41.353467" longitude="2.174817" windSpeed="3.5" windAngle="SW" windRelative="0" waterTemperature="16" airTemperature="16" timeOffsetUtc="+1.00" timestamp="2026-04-10T06:55:01+02:00" speed="0.1" localTime="06:54" heading="206.2" course="349"/>
        <cams>
            <cam name="Backbord" thumb="https://media.aida.de/webcam/aidacosma_left_76px.jpg" link="https://media.aida.de/webcam/aidacosma_left_625px.jpg" img="https://media.aida.de/webcam/aidacosma_left_625px.jpg" captured="20260410064416"/>
            <cam name="Voraus" thumb="https://media.aida.de/webcam/aidacosma_ahead_76px.jpg" link="https://media.aida.de/webcam/aidacosma_ahead_625px.jpg" img="https://media.aida.de/webcam/aidacosma_ahead_625px.jpg" captured="20260410064416"/>
            <cam name="Steuerbord" thumb="https://media.aida.de/webcam/aidacosma_right_76px.jpg" link="https://media.aida.de/webcam/aidacosma_right_625px.jpg" img="https://media.aida.de/webcam/aidacosma_right_625px.jpg" captured="20260410064416"/>
        </cams>
    </ship>
</aidashipmap>